{"is_source_file": true, "format": "TypeScript", "description": "This file is the main server entry point for an Angular application, responsible for bootstrapping the root component with server-specific configuration.", "external_files": ["@angular/platform-browser", "./app/app.component", "./app/app.config.server"], "external_methods": ["bootstrapApplication"], "published": ["bootstrap"], "classes": [], "methods": [{"name": "bootstrap", "description": "Function that initiates the application bootstrap process with the root component and server configuration."}], "calls": ["bootstrapApplication(AppComponent, config)"], "search-terms": ["main.server.ts", "bootstrap application", "Angular server bootstrap", "AppComponent", "app.config.server"], "state": 2, "file_id": 6, "knowledge_revision": 30, "git_revision": "58f2bea065756a7cf0bb609ea3af5eb219fa5222", "ctags": [{"_type": "tag", "name": "bootstrap", "path": "/home/kavia/workspace/code-generation/tic-tac-toe-online-8537-8546/tic_tac_toe_frontend/src/main.server.ts", "pattern": "/^const bootstrap = () => bootstrapApplication(AppComponent, config);$/", "language": "TypeScript", "kind": "constant"}], "hash": "2f67d3e7163632b8f077f15a810789b6", "format-version": 4, "code-base-name": "tic_tac_toe_frontend", "filename": "tic_tac_toe_frontend/src/main.server.ts", "revision_history": [{"30": "58f2bea065756a7cf0bb609ea3af5eb219fa5222"}]}